AUTHORS.rst
CONTRIBUTING.rst
HISTORY.rst
LICENSE
MANIFEST.in
README.rst
setup.cfg
setup.py
docs/Makefile
docs/authors.rst
docs/conf.py
docs/contributing.rst
docs/history.rst
docs/index.rst
docs/installation.rst
docs/make.bat
docs/readme.rst
docs/usage.rst
helloworld_20200320/__init__.py
helloworld_20200320/cli.py
helloworld_20200320/helloworld_20200320.py
helloworld_20200320.egg-info/PKG-INFO
helloworld_20200320.egg-info/SOURCES.txt
helloworld_20200320.egg-info/dependency_links.txt
helloworld_20200320.egg-info/entry_points.txt
helloworld_20200320.egg-info/not-zip-safe
helloworld_20200320.egg-info/requires.txt
helloworld_20200320.egg-info/top_level.txt
tests/__init__.py
tests/test_helloworld_20200320.py